kjz_geo_search_sdk/__init__.py
kjz_geo_search_sdk/get_data.py
kjz_geo_search_sdk-1.0.0.dist-info/LICENSE
kjz_geo_search_sdk-1.0.0.dist-info/METADATA
kjz_geo_search_sdk-1.0.0.dist-info/WHEEL
kjz_geo_search_sdk-1.0.0.dist-info/top_level.txt
kjz_geo_search_sdk-1.0.0.dist-info/RECORD
