Metadata-Version: 2.1
Name: kjz-geo-search-sdk
Version: 1.0.0
Summary: 空间站数据搜索SDK
Author: yc
Author-email: liu.fei@yunstorm.com
License: MIT
Classifier: Programming Language :: Python :: 3
License-File: LICENSE
Requires-Dist: requests
